sansio_jsonrpc/__init__.py
sansio_jsonrpc/exc.py
sansio_jsonrpc/main.py
sansio_jsonrpc/types.py
sansio_jsonrpc-0.2.0.dist-info/WHEEL
sansio_jsonrpc-0.2.0.dist-info/METADATA
sansio_jsonrpc-0.2.0.dist-info/RECORD
