Metadata-Version: 2.1
Name: sansio-jsonrpc
Version: 0.2.0
Summary: JSON-RPC v2.0 Sans I/O
Home-page: https://github.com/hyperiongray/sansio-jsonrpc
License: MIT
Author: Mark E. Haase
Author-email: mehaase@gmail.com
Requires-Python: >=3.7,<4.0
Classifier: Development Status :: 3 - Alpha
Classifier: Intended Audience :: Developers
Classifier: License :: OSI Approved :: MIT License
Classifier: Programming Language :: Python :: 3
Classifier: Programming Language :: Python :: 3.7
Classifier: Programming Language :: Python :: 3.8
Classifier: Topic :: Internet
